idsl_gauge/__init__.py
idsl_gauge-1.0.1.dist-info/LICENSE
idsl_gauge-1.0.1.dist-info/METADATA
idsl_gauge-1.0.1.dist-info/WHEEL
idsl_gauge-1.0.1.dist-info/top_level.txt
idsl_gauge-1.0.1.dist-info/RECORD
